{".class": "MypyFile", "_fullname": "graphistry.util", "is_partial_stub_package": false, "is_stub": false, "names": {".class": "SymbolTable", "LooseVersion": {".class": "SymbolTableNode", "cross_ref": "distutils.version.LooseVersion", "kind": "Gdef"}, "StrictVersion": {".class": "SymbolTableNode", "cross_ref": "distutils.version.StrictVersion", "kind": "Gdef"}, "__doc__": {".class": "SymbolTableNode", "kind": "Gdef", "node": {".class": "Var", "flags": [], "fullname": "graphistry.util.__doc__", "name": "__doc__", "type": "builtins.str"}}, "__file__": {".class": "SymbolTableNode", "kind": "Gdef", "node": {".class": "Var", "flags": [], "fullname": "graphistry.util.__file__", "name": "__file__", "type": "builtins.str"}}, "__name__": {".class": "SymbolTableNode", "kind": "Gdef", "node": {".class": "Var", "flags": [], "fullname": "graphistry.util.__name__", "name": "__name__", "type": "builtins.str"}}, "__package__": {".class": "SymbolTableNode", "kind": "Gdef", "node": {".class": "Var", "flags": [], "fullname": "graphistry.util.__package__", "name": "__package__", "type": "builtins.str"}}, "cmp": {".class": "SymbolTableNode", "kind": "Gdef", "node": {".class": "Var", "flags": ["is_suppressed_import"], "fullname": "graphistry.util.cmp", "name": "cmp", "type": {".class": "AnyType", "missing_import_name": "graphistry.util.cmp", "source_any": null, "type_of_any": 3}}}, "compare_versions": {".class": "SymbolTableNode", "kind": "Gdef", "node": {".class": "FuncDef", "arg_kinds": [0, 0], "arg_names": ["v1", "v2"], "flags": [], "fullname": "graphistry.util.compare_versions", "name": "compare_versions", "type": null}}, "error": {".class": "SymbolTableNode", "kind": "Gdef", "node": {".class": "FuncDef", "arg_kinds": [0], "arg_names": ["msg"], "flags": [], "fullname": "graphistry.util.error", "name": "error", "type": null}}, "fingerprint": {".class": "SymbolTableNode", "kind": "Gdef", "node": {".class": "FuncDef", "arg_kinds": [], "arg_names": [], "flags": [], "fullname": "graphistry.util.fingerprint", "name": "fingerprint", "type": null}}, "hashlib": {".class": "SymbolTableNode", "cross_ref": "hashlib", "kind": "ModuleRef"}, "in_ipython": {".class": "SymbolTableNode", "kind": "Gdef", "node": {".class": "FuncDef", "arg_kinds": [], "arg_names": [], "flags": [], "fullname": "graphistry.util.in_ipython", "name": "in_ipython", "type": null}}, "make_iframe": {".class": "SymbolTableNode", "kind": "Gdef", "node": {".class": "FuncDef", "arg_kinds": [0, 0, 0], "arg_names": ["raw_url", "height", "protocol"], "flags": [], "fullname": "graphistry.util.make_iframe", "name": "make_iframe", "type": null}}, "merge_two_dicts": {".class": "SymbolTableNode", "kind": "Gdef", "node": {".class": "FuncDef", "arg_kinds": [0, 0], "arg_names": ["a", "b"], "flags": [], "fullname": "graphistry.util.merge_two_dicts", "name": "merge_two_dicts", "type": null}}, "p": {".class": "SymbolTableNode", "cross_ref": "platform", "kind": "ModuleRef"}, "print_function": {".class": "SymbolTableNode", "cross_ref": "__future__.print_function", "kind": "Gdef"}, "random": {".class": "SymbolTableNode", "cross_ref": "random", "kind": "ModuleRef"}, "random_string": {".class": "SymbolTableNode", "kind": "Gdef", "node": {".class": "FuncDef", "arg_kinds": [0], "arg_names": ["length"], "flags": [], "fullname": "graphistry.util.random_string", "name": "random_string", "type": null}}, "range": {".class": "SymbolTableNode", "cross_ref": "builtins.range", "kind": "Gdef"}, "str": {".class": "SymbolTableNode", "cross_ref": "builtins.str", "kind": "Gdef"}, "string": {".class": "SymbolTableNode", "cross_ref": "string", "kind": "ModuleRef"}, "sys": {".class": "SymbolTableNode", "cross_ref": "sys", "kind": "ModuleRef"}, "uuid": {".class": "SymbolTableNode", "cross_ref": "uuid", "kind": "ModuleRef"}, "warn": {".class": "SymbolTableNode", "kind": "Gdef", "node": {".class": "FuncDef", "arg_kinds": [0], "arg_names": ["msg"], "flags": [], "fullname": "graphistry.util.warn", "name": "warn", "type": null}}}, "path": "/home/cwharris/src/pygraphistry/graphistry/util.py"}
